{
  "metadata": {
    "id": 2,
    "data_type": "music",
    "title": "Music"
  },
  "items": [
    {
      "id": 1,
      "name": "Cosimo and the Hot Coals - Blues dell'Emigrante (Live from Villa Bossi)",
      "description": "",
      "channel": "youtube",
      "tags": [],
      "url": "https://www.youtube.com/embed/OIp97UMmqgQ?si=JAHPbqMqybV_7wbo"
    },
    {
      "id": 2,
      "name": "St. James Infirmary - Cosimo and the Hot Coals (Live from Villa Bossi)",
      "description": "",
      "channel": "youtube",
      "tags": [],
      "url": "https://www.youtube.com/embed/QFPMWKTiSkI?si=gFFdo9xNKtXGBxsq"
    },
    {
      "id": 3,
      "name": "Sail North - Bones (Official Lyric Video)",
      "description": "",
      "channel": "youtube",
      "tags": [],
      "url": "https://www.youtube.com/embed/9YR2CzCj0w4?si=kLo4QOqVHgLzX1uL"
    },
    {
      "id": 4,
      "name": "Sail North - Tale of The Shadow (Official Lyric Video)",
      "description": "",
      "channel": "youtube",
      "tags": [],
      "url": "https://www.youtube.com/embed/TvtcwsouILY?si=2kyALCjobWwn7J3X"
    },
    {
      "id": 5,
      "name": "Auld Lang Syne ~ Guy Lombardo ~ 1947 Version",
      "description": "",
      "channel": "youtube",
      "tags": [],
      "url": "https://www.youtube.com/embed/adwni-Jt8qQ?si=P2m1nmwHaNYQCtkr"
    },
    {
      "id": 6,
      "name": "JÖRMUNGANDR (VolfgangTwins) Heavy Viking Music",
      "description": "",
      "channel": "youtube",
      "tags": [],
      "url": "https://www.youtube.com/embed/IIHFxeN4BW4?si=pfIEfaf4jXl0emuW"
    },
    {
      "id": 7,
      "name": "PALLADIO - Asturia Quartet",
      "description": "",
      "channel": "youtube",
      "tags": [],
      "url": "https://www.youtube.com/embed/oTf5qi2J6PM?si=l3rmz8Ntp2EnGdsb"
    },
    {
      "id": 8,
      "name": "Zorba the Greek",
      "description": "The Dance of the Zorba",
      "channel": "youtube",
      "tags": ["movies", "Anthony Quinn", "Greek", "ethnic"],
      "url": "https://www.youtube.com/embed/BS0w3Wkric8?si=puz0D4gzASTX0w89"
    },
    {
      "id": 9,
      "name": "Zorba Emmetron",
      "description": "The Dance of the Zorba",
      "channel": "youtube",
      "tags": ["Greek", "ethnic"],
      "url": "https://www.youtube.com/embed/LYG5l9SQLp8?si=-PhkiZWvGoavRPU7"
    },
    {
      "id": 10,
      "name": "Lee Marvin Wandering Star 1969 HD",
      "description": "Wandering Star",
      "channel": "youtube",
      "section": "Movies",
      "tags": ["Movies", "Lee Marvin"],
      "url": "https://www.youtube.com/embed/-jYk5u9vKfA?si=ccYUCfLgnxQ7lLao"
    },
    {
      "id": 11,
      "name": "Harve Presnell They call the Wind Maria remastered",
      "description": "They call the Wind Maria",
      "channel": "youtube",
      "section": "Movies",
      "tags": ["movies", "Harve Presnell"],
      "url": "https://www.youtube.com/embed/ByqYEzugleE?si=sR0XUX0K8vfucXwa"
    },
    {
      "id": 12,
      "name": "Vivaldi: Four Seasons - Winter",
      "description": "Four Seasons - Winter",
      "channel": "youtube",
      "artist": "Claudio Constantini",
      "tags": ["Vivaldi", "Constantini"],
      "url": "https://www.youtube.com/embed/JUPo5SG5GCg?si=vZsWPFetmcZG06Jf"
    },
    {
      "id": 12,
      "name": "Tchaikovsky: The Nutcracker",
      "description": "The Nutcracker",
      "channel": "youtube",
      "artist": "Claudio Constantini",
      "tags": ["Tchaikovsky", "Constantini"],
      "url": "https://www.youtube.com/embed/hYADTPwa9lk?si=66dOeV25dwRegPrp"
    },
    {
      "id": 0,
      "name": "La Foule - Reminiscencias",
      "description": "La Foule",
      "channel": "youtube",
      "artist": "Claudio Constantini",
      "tags": ["Constantini"],
      "url": "https://www.youtube.com/embed/GUppXhIataY?si=0syUxna6NeGjmDSn"
    },
    {
      "id": 0,
      "name": "Autumn Leaves in Baroque style",
      "description": "Autumn Leaves",
      "channel": "youtube",
      "artist": "Claudio Constantini",
      "tags": ["Constantini"],
      "url": "https://www.youtube.com/embed/XliHqe4dhIY?si=y0wi2L_cN40l3UDa"
    },
    {
      "id": 0,
      "name": "Passacaglia – Handel/Halvorsen (Piano Solo)",
      "description": "Passacaglia",
      "channel": "youtube",
      "artist": "Halvorsen",
      "tags": ["Handel", "Halvorsen"],
      "url": "https://www.youtube.com/embed/GAIZxaToV2A?si=Z2P51A85fr3a6M44"
    },
    {
      "id": 0,
      "name": "Disturbed - The Sound Of Silence (Official Music Video) [4K UPGRADE]",
      "description": "The Sound Of Silence",
      "channel": "youtube",
      "artist": "Disturbed",
      "tags": ["Simon & Garfunkel", "Disturbed"],
      "url": "https://www.youtube.com/embed/u9Dg-g7t2l4?si=drUAeZFhRIpq7Xp5"
    },
    {
      "id": 0,
      "name": "Imagine - Julian Lennon",
      "description": "Imagine",
      "channel": "youtube",
      "artist": "Julian Lennon",
      "tags": [],
      "url": "https://www.youtube.com/embed/NicWjYMPDG0?si=NpcDfYeWZxVRmkjs"
    },
    {
      "id": 200,
      "name": "The Conservation of The Assassination of Archimedes Narrated Version",
      "description": "Art Restoration",
      "channel": "youtube",
      "artist": "Baumgartner Restoration",
      "tags": ["Art Restoration"],
      "url": "https://www.youtube.com/embed/v1Mjc4zNfY4?si=jPyMdodMf6zU1b2Q"
    },
    {
      "id": 201,
      "name": "Conserving one of the oldest photographs in MoMA's collection",
      "description": "The Museum of Modern Art",
      "channel": "youtube",
      "artist": "The Museum of Modern Art",
      "tags": ["Art Restoration"],
      "url": "https://www.youtube.com/embed/1O88Vc-cC4I?si=SWiN0Bc_TB0lr2Gd"
    },
    {
      "id": 13,
      "name": "Lou Monte - Dominick The Donkey (HQ Audio)",
      "description": "Dominick The Donkey",
      "channel": "youtube",
      "artist": "Lou Monte",
      "tags": ["Christmas", "Lou Monte"],
      "url": "https://www.youtube.com/embed/Ca5wXojemRM?si=wJWYqbFiLy63d1c7"
    },
    {
      "id": 14,
      "name": "Leonard Nimoy: The Ballad of Bilbo Baggins - Full Album Version",
      "description": "The Ballad of Bilbo Baggins",
      "channel": "youtube",
      "artist": "Leonard Nimoy",
      "tags": ["Leonard Nimoy"],
      "url": "https://www.youtube.com/embed/BC35cQKHwzg?si=qEvK2Pyc7WKWJC25"
    },
    {
      "id": 15,
      "name": "Dean Martin - That's Amore",
      "description": "That's Amore",
      "channel": "youtube",
      "artist": "Dean Martin",
      "tags": ["Dean Martin", "Italian"],
      "url": "https://www.youtube.com/embed/OnFlx2Lnr9Q?si=9Lr5vZAZHscjuAC8"
    },
    {
      "id": 16,
      "name": "The Muppets \"Mahna Mahna\" on The Ed Sullivan Show",
      "description": "Mahna Mahna",
      "channel": "youtube",
      "artist": "Muppets",
      "section": "Muppets",
      "tags": ["Muppets"],
      "url": "https://www.youtube.com/embed/zb47CstE7R4?si=3pN4qEGZB9t4p-SX"
    },
    {
      "id": 17,
      "name": "Rainbow Connection by Kermit the Frog from The Muppet Movie",
      "description": "Rainbow Connection",
      "channel": "youtube",
      "artist": "Muppets",
      "tags": ["Muppets"],
      "url": "https://www.youtube.com/embed/WS3Lkc6Gzlk?si=3C2ZK1hd0TLGNb_h"
    },
    {
      "id": 0,
      "name": "The Seekers - I'll Never Find Another You (HQ Stereo, 1964/'68)",
      "description": "I'll Never Find Another You",
      "channel": "youtube",
      "artist": "The Seekers",
      "section": "The Seekers",
      "tags": [""],
      "url": "https://www.youtube.com/embed/wZf41UudAbI?si=YnvXIFsPAFeAspE3"
    },
    {
      "id": 0,
      "name": "The Seekers - Georgy Girl (1967 - Stereo)",
      "description": "Georgy Girl",
      "channel": "youtube",
      "artist": "The Seekers",
      "section": "The Seekers",
      "tags": [""],
      "url": "https://www.youtube.com/embed/wsIbfYEizLk?si=PwewzPcAwih1Dq0m"
    },
    {
      "id": 0,
      "name": "The Seekers - Turn, Turn, Turn (HQ Stereo, 1966/67)",
      "description": "Turn, Turn, Turn",
      "channel": "youtube",
      "artist": "The Seekers",
      "section": "The Seekers",
      "tags": [""],
      "url": "https://www.youtube.com/embed/VRg9NkIdjVs?si=KiNokk4NW9J9KjS-"
    },
    {
      "id": 0,
      "name": "\"The Girl from Ipanema\" Astrud Gilberto, João Gilberto and Stan Getz",
      "description": "The Girl from Ipanema",
      "channel": "youtube",
      "artist": "Astrud Gilberto",
      "tags": [""],
      "url": "https://www.youtube.com/embed/c5QfXjsoNe4?si=PPEEVMSGaKy1lzer"
    },
    {
      "id": 0,
      "name": "Dave Brubeck - Take Five",
      "description": "Take Five",
      "channel": "youtube",
      "artist": "Dave Brubeck",
      "tags": [""],
      "url": "https://www.youtube.com/embed/vmDDOFXSgAs?si=aA06r2Qt7cAjSIIE"
    },
    {
      "id": 0,
      "name": "Songs that use 5/4 time (discussion on Take Five)",
      "description": "",
      "channel": "youtube",
      "artist": "",
      "tags": [""],
      "url": "https://www.youtube.com/embed/KQ76-WiFTlo?si=KB4_Y-6cG3POoq84"
    },
    {
      "id": 0,
      "name": "Mary Hopkin - Those Were The Days - 1968",
      "description": "Those Were The Days",
      "channel": "youtube",
      "artist": "Mary Hopkin",
      "tags": [""],
      "url": "https://www.youtube.com/embed/y3KEhWTnWvE?si=OyYlZPKNpvtmH1Mg"
    },
    {
      "id": 0,
      "name": "Zager & Evans - In the Year 2525",
      "description": "In the Year 2525",
      "channel": "youtube",
      "artist": "Zager & Evans",
      "tags": [""],
      "url": "https://www.youtube.com/embed/zKQfxi8V5FA?si=PdqrrmSMLuADbdgE"
    },
    {
      "id": 0,
      "name": "Love Story (Where do I begin):Shirley Bassey",
      "description": "Love Story (Where do I begin)",
      "channel": "youtube",
      "artist": "Shirley Bassey",
      "tags": [""],
      "url": "https://www.youtube.com/embed/tdVFApo0EXg?si=F2eoueHwJufS-r1X"
    },
    {
      "id": 0,
      "name": "Edith Piaf - La Vie En Rose",
      "description": "La Vie En Rose",
      "channel": "youtube",
      "artist": "Edith Piaf",
      "tags": [""],
      "url": "https://www.youtube.com/embed/kFzViYkZAz4?si=ZZ-cnyalc0upCMiU"
    },
    {
      "id": 0,
      "name": "Edith Piaf Je Ne Regrette Rien Live Paris Olympia 1960",
      "description": "Je Ne Regrette Rien",
      "channel": "youtube",
      "artist": "Edith Piaf",
      "tags": [""],
      "url": "https://www.youtube.com/embed/KoYHWgj1Gcs?si=CTE7r6M6ogZNoerE"
    },
    {
      "id": 0,
      "name": "Jessie J - Bang Bang ft. Ariana Grande, Nicki Minaj",
      "description": "Bang Bang",
      "channel": "youtube",
      "artist": "Ariana Grande",
      "tags": [""],
      "url": "https://www.youtube.com/embed/0HDdjwpPM3Y?si=Kqz957abvZ26Clyd"
    },
    {
      "id": 0,
      "name": "Nancy Sinatra - Bang-Bang (My Baby Shot Me Down) - 1967",
      "description": "Bang-Bang (My Baby Shot Me Down)",
      "channel": "youtube",
      "artist": "Nancy Sinatra",
      "tags": [""],
      "url": "https://www.youtube.com/embed/7FNse1n7pSs?si=Epvc7GrQWhu_oyjS"
    },
    {
      "id": 0,
      "name": "Nancy Sinatra - These Boots Are Made For Walkin' (Official Music Video)",
      "description": "These Boots Are Made For Walkin'",
      "channel": "youtube",
      "artist": "Nancy Sinatra",
      "tags": [""],
      "url": "https://www.youtube.com/embed/GM1kzbAgo_E?si=0aHnAsW2oULzJ8O7"
    },
    {
      "id": 0,
      "name": "Dalida Bang Bang - 1966 - Dalida officiel",
      "description": "Bang-Bang (My Baby Shot Me Down)",
      "channel": "youtube",
      "artist": "Dalida",
      "tags": [""],
      "url": "https://www.youtube.com/embed/WUVJY4N9bbI?si=LZlL8KrZdNe8dm1H"
    },
    {
      "id": 0,
      "name": "Love Potion Number 9, The Searchers",
      "description": "Love Potion Number 9",
      "channel": "youtube",
      "artist": "The Searchers",
      "tags": [""],
      "url": "https://www.youtube.com/embed/7rXhXLsNJL8?si=cvNeo5h6O7TvnrjI"
    },
    {
      "id": 0,
      "name": "Dalida Bang Bang - 1966 - Dalida officiel",
      "description": "Bang-Bang (My Baby Shot Me Down)",
      "channel": "youtube",
      "artist": "Dalida",
      "tags": [""],
      "url": "https://www.youtube.com/embed/WUVJY4N9bbI?si=LZlL8KrZdNe8dm1H"
    },
    {
      "id": 0,
      "name": "Some Say The Devil is Dead",
      "description": "",
      "channel": "youtube",
      "artist": "Ceol",
      "rating": 0,
      "tags": ["Irish"],
      "url": "https://www.youtube.com/embed/oqyCeC6oMHU?si=A-BQNeIC04ZwB0-m"
    },
    {
      "id": 0,
      "name": "The Ferryman",
      "description": "",
      "channel": "youtube",
      "artist": "Ceol",
      "rating:": 1,
      "tags": ["Irish"],
      "url": "https://www.youtube.com/embed/KAGWiIioscQ?si=Gf2PAWSEFYHhpl9I"
    },
    {
      "id": 0,
      "name": "The Dead South - You Are My Sunshine [Official Music Video]",
      "description": "You Are My Sunshine",
      "channel": "youtube",
      "artist": "The Dead South",
      "ranking": 0,
      "tags": ["Banjo"],
      "url": "https://www.youtube.com/embed/1MevYCdn5S8?si=c2j0l2j7BTF33wcS"
    },
    {
      "id": 0,
      "name": "Pour Some Sugar On Me - Def Leppard (1960s Early Soul Style Cover) feat. Kyndle Wylde",
      "description": "Pour Some Sugar On Me",
      "channel": "youtube",
      "artist": "Postmodern Jukebox",
      "tags": ["Postmodern Jukebox"],
      "url": "https://www.youtube.com/embed/ilClbWTYgfw?si=thudG4IrbozjUVa-"
    },
    {
      "id": 0,
      "name": "Creep - Vintage Postmodern Jukebox Radiohead Cover ft. Haley Reinhart",
      "description": "Creep",
      "channel": "youtube",
      "artist": "Postmodern Jukebox",
      "tags": ["Postmodern Jukebox"],
      "url": "https://www.youtube.com/embed/m3lF2qEA2cw?si=wrSzpEAFDuFNnjPa"
    },
    {
      "id": 0,
      "name": "Retour sur la Fête des Lumières 2023 !",
      "description": "Festival of Lights 2023 Lyon, France",
      "channel": "youtube",
      "artist": "",
      "tags": ["2023"],
      "url": "https://www.youtube.com/embed/sGBTVngHvug?si=6dxiaiYCQ2k8G5MF"
    },
    {
      "id": 0,
      "name": "Fête des lumières 2023 Lyon - Gare Saint Paul : 'Nouvelle Vague' (artistes divers)",
      "description": "Festival of Lights 2023 Lyon, France",
      "channel": "youtube",
      "artist": "",
      "tags": ["2023"],
      "url": "https://www.youtube.com/embed/M3Ne0YIyZ44?si=CKCGSKFUTRvS8gMn"
    },
    {
      "id": 0,
      "name": "Fête des lumières 2023 - Sign – Place de la République",
      "description": "Festival of Lights 2023 Lyon, France",
      "channel": "youtube",
      "artist": "",
      "tags": ["2023"],
      "url": "https://www.youtube.com/embed/r_dXy5EDgBE?si=GOAYkY0iDcTjXV4p"
    },
    {
      "id": 0,
      "name": "Massed Pipes & Drums Parade, Edinburgh Hogmanay 2023",
      "description": "",
      "channel": "youtube",
      "artist": "",
      "time": "4:12",
      "tags": ["Edinburgh", "2023", "Hogmanay", "Bagpipes"],
      "url": "https://www.youtube.com/embed/FHHBLEcObvM?si=BpteQeFNG59R-ToK"
    },
    {
      "id": 0,
      "name": "M.A.S.H. Theme Song",
      "description": "",
      "channel": "youtube",
      "artist": "",
      "tags": [""],
      "url": "https://www.youtube.com/embed/GIGYLBVjYZA?si=i9TPS3z5Y-kje-9O"
    },
    {
      "id": 0,
      "name": "Gilligan's Island Theme Song",
      "description": "",
      "channel": "youtube",
      "artist": "",
      "tags": [""],
      "url": "https://www.youtube.com/embed/yfSLuEj99d0?si=wS1-pndgDeQqsMq6"
    },
    {
      "id": 0,
      "name": "Green Acres Intro~HD with Lyrics(Best version on youtube)",
      "description": "",
      "channel": "youtube",
      "artist": "",
      "tags": [""],
      "url": "https://www.youtube.com/embed/wzT1kO_-xbQ?si=Iq5aixqikJTWcMGl"
    },
    {
      "id": 0,
      "name": "Addam's Family Opening Theme Song With Lyrics(Best Version On Youtube)",
      "description": "",
      "channel": "youtube",
      "artist": "",
      "tags": [""],
      "url": "https://www.youtube.com/embed/GFhLYnzGSno?si=5UpWUOr3ikUZRmAh"
    },
    {
      "id": 0,
      "name": "The Munsters Theme Song",
      "description": "",
      "channel": "youtube",
      "artist": "",
      "tags": ["https://www.youtube.com/embed/JdrbLvFJkB4?si=-LHvUovqP6-z1e_H"],
      "url": ""
    },
    {
      "id": 0,
      "name": "The Jetsons Theme Song",
      "description": "",
      "channel": "youtube",
      "artist": "",
      "tags": [""],
      "url": "https://www.youtube.com/embed/tTq6Tofmo7E?si=l8zIoU8ikh3VLVDZ"
    },
    {
      "id": 0,
      "name": "The Flintstones Opening and Closing Theme 1960 1966",
      "description": "",
      "channel": "youtube",
      "artist": "",
      "tags": [""],
      "url": "https://www.youtube.com/embed/uq7noaMwLfg?si=KO7cDtuOki83hoO5"
    },
    {
      "id": 0,
      "name": "Coca-Cola  \"I'd like to buy the world a Coke\" 1971",
      "description": "",
      "channel": "youtube",
      "artist": "",
      "tags": [""],
      "url": "https://www.youtube.com/embed/1VM2eLhvsSM?si=fSJRP17HLm2a_NWA"
    },
    {
      "id": 0,
      "name": "Let's All go to the Lobby! Intermission Bumper 4K Update",
      "description": "",
      "channel": "youtube",
      "artist": "",
      "tags": [""],
      "url": "https://www.youtube.com/embed/lm6IU6V-dE8?si=874c845kOeamlLJF"
    },
    {
      "id": 0,
      "name": "Eurythmics, Annie Lennox, Dave Stewart - Sweet Dreams (Are Made Of This) (Official Video)",
      "description": "",
      "channel": "youtube",
      "artist": "Eurythmics",
      "tags": ["Eurythmics", "Annie Lennox"],
      "url": "https://www.youtube.com/embed/qeMFqkcPYcg?si=xF7-B2rQIYxpuUyp"
    },
    {
      "id": 0,
      "name": "Annie Lennox - Walking on Broken Glass (Official Video)",
      "description": "",
      "channel": "youtube",
      "artist": "Annie Lennox",
      "tags": ["Annie Lennox"],
      "url": "https://www.youtube.com/embed/y25stK5ymlA?si=b46ONxbcaRuRcRsI"
    },
    {
      "id": 0,
      "name": "Annie Lennox - No More \"I Love You's\" (Official Video)",
      "description": "",
      "channel": "youtube",
      "artist": "Annie Lennox",
      "tags": ["Annie Lennox"],
      "url": "https://www.youtube.com/embed/NSkboTTTmpg?si=qHb18kXNJpP5wJiv"
    },
    {
      "id": 0,
      "name": "Annie Lennox - Why (Official Music Video)",
      "description": "",
      "channel": "youtube",
      "artist": "Annie Lennox",
      "tags": ["Annie Lennox"],
      "url": "https://www.youtube.com/embed/HG7I4oniOyA?si=qDAGCi5K1DyRHGjJ"
    },
    {
      "id": 0,
      "name": "Annie Lennox - A Whiter Shade of Pale (Remastered)",
      "description": "",
      "channel": "youtube",
      "artist": "Annie Lennox",
      "tags": ["Annie Lennox"],
      "url": "https://www.youtube.com/embed/VZqPoriYXho?si=suDE7Rq_i45vJsQi"
    },
    {
      "id": 0,
      "name": "Masquerade - Motion Picture Cast | Andrew Lloyd Webber’s The Phantom of the Opera Soundtrack",
      "description": "Masquerade",
      "channel": "youtube",
      "artist": "Andrew Lloyd Webber",
      "tags": ["Andrew Lloyd Webber"],
      "url": "https://www.youtube.com/embed/mON5dbdm63M?si=mcq3sMpY36_rtXex"
    },
    {
      "id": 0,
      "name": "Diva Dance from The Fifth Element. Full version.",
      "description": "The Fifth Element",
      "channel": "youtube",
      "artist": "",
      "tags": ["Movies", "The Fifth Element"],
      "url": "https://www.youtube.com/embed/a7Dh5QoXv2c?si=fL75BFLcHLsoSTCJ"
    },
    {
      "id": 0,
      "name": "Deliverance • Dueling Banjos • Arthur Smith, Eric Weissberg & Steve Mandell",
      "description": "Dueling Banjos",
      "channel": "youtube",
      "artist": "",
      "tags": ["Movies", "Deliverance"],
      "url": "https://www.youtube.com/embed/NFutge4xn3w?si=oFNTjD8T8VUqOM3w"
    },
    {
      "id": 0,
      "name": "Dusty Springfield / Windmills Of Your Mind",
      "description": "Windmills of Your Mind",
      "channel": "youtube",
      "artist": "Dusty Springfield",
      "tags": [""],
      "url": "https://www.youtube.com/embed/qKV9bK-CBXo?si=iU6HjaxeYoH3OGde"
    },
    {
      "id": 0,
      "name": "The Knights of Ni finally get their shrubbery",
      "description": "The Knights of Ni",
      "channel": "youtube",
      "artist": "Monty Python",
      "tags": ["Movies", "Monty Python"],
      "url": "https://www.youtube.com/embed/RZvsGdJP3ng?si=lneb_H3MammAYQDZ"
    },
    {
      "id": 0,
      "name": "Monty Python - \"Not Dead Yet\" Scene (HD)",
      "description": "Not Dead Yet",
      "channel": "youtube",
      "artist": "Monty Python",
      "tags": ["Movies", "Monty Python"],
      "url": "https://www.youtube.com/embed/Jdf5EXo6I68?si=xX-y0mUVBMrK0zxd"
    },
    {
      "id": 0,
      "name": "\"The Ladies Who Lunch\" with Meryl Streep, Christine Baranski & Audra McDonald (Official Video)",
      "description": "The Ladies Who Lunch",
      "channel": "youtube",
      "artist": "",
      "tags": [],
      "url": "https://www.youtube.com/embed/-mBA9tNdolg?si=vIoM0rGtv2XmnydI"
    },
    {
      "id": 0,
      "name": "Pink Panther Theme | double bass quintet | Božo Paradžik & students",
      "description": "Pink Panther Theme",
      "channel": "youtube",
      "artist": "Henri Mancini",
      "tags": [],
      "url": "https://www.youtube.com/embed/SRIIO408ats?si=xE0kUih-ba0iBy8s"
    },
    {
      "id": 0,
      "name": "Scarborough Fair | Pure Hammered Dulcimer | Joshua Messick",
      "description": "Scarborough Fair",
      "channel": "youtube",
      "artist": "Joshua Messick",
      "tags": ["Joshua Messick"],
      "url": "https://www.youtube.com/embed/PMPFaKpF1SM?si=eWHkaEoU6yCXplJs"
    },
    {
      "id": 0,
      "name": "Dark Ballad Of A Warrior. Epic Medieval Ballad. Hurdy-Gurdy Solo",
      "description": "Dark Ballad Of A Warrior",
      "channel": "youtube",
      "artist": "",
      "tags": [],
      "url": "https://www.youtube.com/embed/0dPHRxvs3KY?si=uj75L5tcvAU2qq3T"
    },
    {
      "id": 0,
      "name": "Tuba Skinny - Jubilee Stomp - Royal Street I",
      "description": "Jubilee Stomp",
      "channel": "youtube",
      "artist": "Tuba Skinny",
      "tags": ["New Orleans"],
      "url": "https://www.youtube.com/embed/jft3BVoxqjo?si=koKGtj0zWivBLfEB"
    },
    {
      "id": 0,
      "name": "Les Yeux Noirs (Dark Eyes) | Django Reinhardt | Pomplamoose ft. The Vignes Rooftop Revival",
      "description": "Dark Eyes",
      "channel": "youtube",
      "artist": "Django Reinhardt",
      "tags": [],
      "url": "https://www.youtube.com/embed/gfiqW1WaGbw?si=igFR1wssHVAFMKws"
    },
    {
      "id": 0,
      "name": "Cajun Music With Pays D’en Haut (Tit Galop Pour Mamou)",
      "description": "",
      "channel": "youtube",
      "artist": "Pays D’en Haut",
      "tags": ["Cajun"],
      "url": "https://www.youtube.com/embed/AFUl28YWVV4?si=N8MV5cIfvWK1NdAH"
    },
    {
      "id": 0,
      "name": "Angels in Heaven - Chris Rodrigues & the Spoon Lady",
      "description": "Angels in Heaven",
      "channel": "youtube",
      "artist": "Chris Rodrigues",
      "tags": [],
      "url": "https://www.youtube.com/embed/_nLmM9kcBKs?si=q8vKH8-q8rT21BoW"
    },
    {
      "id": 0,
      "name": "(Ghost) Riders In the Sky (American Outlaws: Live at Nassau Coliseum, 1990)",
      "description": "(Ghost) Riders In the Sky",
      "channel": "youtube",
      "artist": "American Outlaws",
      "tags": [],
      "url": "https://www.youtube.com/embed/nOWjX4BpC24?si=ETZP4nK5KqtO6SPU"
    },
    {
      "id": 0,
      "name": "Ghost Riders in the Sky - Southern Raised (bass singer cover)",
      "description": "Ghost Riders in the Sky",
      "channel": "youtube",
      "artist": "Southern Raised",
      "tags": [],
      "url": "https://www.youtube.com/embed/oG85zhpgmJY?si=gyOdzHRAuLR5CW2K"
    },
    {
      "id": 0,
      "name": "Jolene - Southern Raised (live)",
      "description": "Jolene",
      "channel": "youtube",
      "artist": "Southern Raised",
      "tags": [],
      "url": "https://www.youtube.com/embed/td6-pyXw7aQ?si=UUJFqTHNRgb-UzN1"
    },
    {
      "id": 0,
      "name": "Scott Joplin: Maple Leaf Rag",
      "description": "Maple Leaf Rag",
      "channel": "youtube",
      "artist": "Dario Ronchi",
      "tags": [],
      "url": "https://www.youtube.com/embed/bCxLAr_bwpA?si=cJBpIR2Ran90Ddff"
    },
    {
      "id": 0,
      "name": "Miriam Makeba - Pata Pata (Live 1967)",
      "description": "Pata Pata",
      "channel": "youtube",
      "artist": "Miriam Makeba",
      "tags": [],
      "url": "https://www.youtube.com/embed/lNeP3hrm__k?si=hC6MeLyE45nuWNfx"
    },
    {
      "id": 0,
      "name": "The Shangri-Las - Leader of the Pack (1964) Stereo HQ Audio",
      "description": "Leader of the Pack",
      "channel": "youtube",
      "artist": "The Shangri-Las",
      "tags": [],
      "url": "https://www.youtube.com/embed/5Ge8_6rtQvs?si=th6oA-BB5WUFeDtm"
    },
    {
      "id": 0,
      "name": "Roger Miller - King Of The Road (1964) 4K",
      "description": "King Of The Road",
      "channel": "youtube",
      "artist": "Roger Miller",
      "tags": [],
      "url": "https://www.youtube.com/embed/4c7D0YsgnrE?si=uDvRnmfan-WS4KnA"
    },
    {
      "id": 0,
      "name": "Dion - The Wanderer (1961) 4K",
      "description": "The Wanderer",
      "channel": "youtube",
      "artist": "Dion",
      "tags": [],
      "url": "https://www.youtube.com/embed/rXqWCeB8Vto?si=bYDGvE_VtaAdQFaQ"
    },
    {
      "id": 0,
      "name": "Gwangalli Drone Show, January 1, 2024",
      "description": "",
      "channel": "youtube",
      "artist": "",
      "tags": ["Drones"],
      "url": "https://www.youtube.com/embed/1O6OzbFu2ho?si=XKkdGexOrQvmOyIk"
    },
    {
      "id": 0,
      "name": "Dmitri Shostakovich - The Second Waltz",
      "description": "The Second Waltz",
      "channel": "youtube",
      "artist": "Dmitri Shostakovich",
      "tags": [],
      "url": "https://www.youtube.com/embed/-2-Zqog-p5c?si=Km5yUB7n5xLf3kzp"
    },
    {
      "id": 0,
      "name": "Por una Cabeza - Carlos Gardel",
      "description": "Por una Cabeza",
      "channel": "youtube",
      "artist": "Carlos Gardel",
      "tags": [],
      "url": "https://www.youtube.com/embed/Gcxv7i02lXc?si=mlfZub0zGtu65V-3"
    },
    {
      "id": 0,
      "name": "Cabaret - Cabaret (1972)",
      "description": "Cabaret",
      "channel": "youtube",
      "artist": "Liza Minelli",
      "tags": ["Movies"],
      "url": "https://www.youtube.com/embed/5QS1l1mSDSo?si=aLUD3ECSMkNy-T2A"
    },
    {
      "id": 0,
      "name": "Chitty Chitty Bang Bang (1968) - Music Box Dance Scene",
      "description": "Music Box Dance Scene",
      "channel": "youtube",
      "artist": "Chitty Chitty Bang Bang",
      "tags": ["Movies"],
      "url": "https://www.youtube.com/embed/L_l2ii_25tc?si=G8JORp9TitD0KOUQ"
    },
    {
      "id": 0,
      "name": "Nessun Dorma from \"An evening with Puccini\"",
      "description": "Nessun Dorma",
      "channel": "youtube",
      "artist": "Jonas Kaufmann",
      "tags": ["Opera", "Puccni"],
      "url": "https://www.youtube.com/embed/-SpKFkjlO8Y?si=sD8WCY67dTAJXmws"
    },
    {
      "id": 0,
      "name": "Parla più piano",
      "description": " Parla più piano",
      "channel": "youtube",
      "artist": "Jonas Kaufmann",
      "tags": [],
      "url": "https://www.youtube.com/embed/nvkVakdV4z8?si=7Gd8eJOnc859OztI"
    },
    {
      "id": 0,
      "name": "Enchanted Tiki Room - 60th Anniversary Disneyland Full Show",
      "description": "Enchanted Tiki Room",
      "comment": "This has always been my favorite show at Disneyland.  It was the last show that Walt Disney worked on prior to his passing.",
      "channel": "youtube",
      "artist": "Disney",
      "tags": ["Disneyland"],
      "url": "https://www.youtube.com/embed/5NSNwyvXZhY?si=tvAWR7fXFveg8pnE"
    },
    {
      "id": 0,
      "name": "Haunted Mansion 2023 - Disneyland Ride [4K POV]",
      "description": "Haunted Mansion",
      "channel": "youtube",
      "artist": "Disney",
      "tags": ["Disneyland"],
      "url": "https://www.youtube.com/embed/xzOnIx0Ypus?si=K6Op8S5VVg28oxjt"
    },
    {
      "id": 0,
      "name": "Pirates of the Caribbean 2023 - Disneyland Ride [4K POV]",
      "description": "Pirates of the Caribbean",
      "channel": "youtube",
      "artist": "Disney",
      "tags": ["Disneyland"],
      "url": "https://www.youtube.com/embed/x2Rd13QWpgk?si=YAmTJNhn-A9BFJdL"
    },
    {
      "id": 0,
      "name": "Indiana Jones Adventure 2024 - Disneyland Ride [4K60 POV]",
      "description": "Indiana Jones Adventure",
      "channel": "youtube",
      "artist": "Disney",
      "tags": ["Disneyland"],
      "url": "https://www.youtube.com/embed/xOJlVmP-L-0?si=JW3uwl_G6ehYkFMD"
    },
    {
      "id": 0,
      "name": "It's A Small World - Disneyland 4K (POV)",
      "description": "It's A Small World",
      "channel": "youtube",
      "artist": "Disney",
      "tags": ["Disneyland"],
      "url": "https://www.youtube.com/embed/Y9LjqwJyoLE?si=be2u8bpfbIiXtbxg"
    },
    {
      "id": 0,
      "name": "Disney Electrical Sky Parade - World Premiere - Disneyland Paris",
      "description": "Disney Electrical Sky Parade",
      "channel": "youtube",
      "date": "2024-01-08",
      "artist": "Disney",
      "tags": ["Disneyland Paris"],
      "url": "https://www.youtube.com/embed/_72-XE3wV4w?si=yHBvXO_84TUjh3Xg"
    },
    {
      "id": 0,
      "name": "Carousel of Progress- Magic Kingdom POV 4K",
      "description": "Carousel of Progress",
      "comments": "One of my favorite shows!",
      "channel": "youtube",
      "artist": "Disney",
      "tags": ["Magic Kingdom"],
      "url": "https://www.youtube.com/embed/Xo4jnlvJmrk?si=1Tu1NMMqSn8uEB9i"
    },
    {
      "id": 0,
      "name": "The Hall of Presidents with Joe Biden Debuts at the Magic Kingdom",
      "description": "The Hall of Presidents",
      "channel": "youtube",
      "artist": "Disney",
      "tags": ["Magic Kingdom"],
      "url": "https://www.youtube.com/embed/77QEaLy1kO8?si=co5qs0NV6PIXJEYv"
    },
    {
      "id": 0,
      "name": "Great Moments with Mr. Lincoln",
      "description": "",
      "channel": "youtube",
      "artist": "Disney",
      "tags": ["Disneyland"],
      "url": "https://www.youtube.com/embed/xqizYMlc3jk?si=hX7JDMdRchKWIkOE"
    },
    {
      "id": 0,
      "name": "Abraham Lincoln Gettysburg speech (Jeff Daniels)",
      "description": "Gettysburg speech",
      "channel": "youtube",
      "artist": "Abraham Lincoln",
      "tags": ["History"],
      "url": "https://www.youtube.com/embed/9TCMHVmNc5w?si=ckz8XtMYq0fyAFGd"
    },
    {
      "id": 0,
      "name": "Woody Guthrie - This Land Is Your Land",
      "description": "This Land Is Your Land",
      "channel": "youtube",
      "artist": "Woody Guthrie",
      "tags": ["Patriotic"],
      "url": "https://www.youtube.com/embed/wxiMrvDbq3s?si=1WqLMq9MN1IhHOu8"
    },
    {
      "id": 0,
      "name": "NYC is Building Anti-Homeless Streets…",
      "description": "Hostile Architecture",
      "channel": "youtube",
      "tags": ["Hostile Architecture"],
      "url": "https://www.youtube.com/embed/AnqUoAEg6f4?si=tVrVibDZbz5GSJgC"
    },
    {
      "id": 0,
      "name": "Piotr Ilich Tchaikovsky - 1812 Overture (Finale)",
      "description": "1812 Overture",
      "channel": "youtube",
      "artist": "Tchaikovsky",
      "tags": ["Tchaikovsky"],
      "url": "https://www.youtube.com/embed/u2W1Wi2U9sQ?si=rhbWbQIaLR0-2fS1"
    },
    {
      "id": 0,
      "name": "Richard Wagner: The Valkyrie - Ride of the Valkyries",
      "description": "The Valkyrie",
      "channel": "youtube",
      "artist": "Richard Wagner",
      "tags": [""],
      "url": "https://www.youtube.com/embed/hQM97_iNXhk?si=4JEWJft-2FmJbsIs"
    },
    {
      "id": 0,
      "name": "The Battle Hymn of the Republic",
      "channel": "youtube",
      "artist": "The United States Army Field Band",
      "tags": ["Patriotic"],
      "url": "https://www.youtube.com/embed/Jy6AOGRsR80?si=gVGYrgxpT4Hhrc50"
    },
    {
      "id": 0,
      "name": "Gomer Pyle, USMC - The Impossible Dream",
      "description": "The Impossible Dream",
      "channel": "youtube",
      "artist": "Jim Nabors",
      "tags": [],
      "url": "https://www.youtube.com/embed/yJlgio-UOng?si=0Dg_O9Yibki7HATR"
    },
    {
      "id": 0,
      "name": "Monty Python - Argument",
      "description": "Argument",
      "channel": "youtube",
      "artist": "Monty Python",
      "tags": ["Monty Python"],
      "url": "https://www.youtube.com/embed/ohDB5gbtaEQ?si=yC6yciStre2-1R5J"
    },
    {
      "id": 0,
      "name": "Monty Python - Dead Parrot",
      "description": "Dead Parrot",
      "channel": "youtube",
      "artist": "Monty Python",
      "tags": ["Monty Python"],
      "url": "https://www.youtube.com/embed/4vuW6tQ0218?si=LHnW1xQg9tv7hH3y"
    },
    {
      "id": 0,
      "name": "Monty Python - The Cheese Shop",
      "description": "The Cheese Shop",
      "channel": "youtube",
      "artist": "Monty Python",
      "tags": ["Monty Python"],
      "url": "https://www.youtube.com/embed/B3KBuQHHKx0?si=-LCn4O0yoFkTCp6u"
    },
    {
      "id": 0,
      "name": "Monty Python - Fish License",
      "description": "Fish License",
      "channel": "youtube",
      "artist": "Monty Python",
      "tags": ["Monty Python"],
      "url": "https://www.youtube.com/embed/pnq96W9jtuw?si=6dA0_-5J6nSBb7HQ"
    },
    {
      "id": 0,
      "name": "The Dead South - Yours to Keep [Official Music Video]",
      "description": "",
      "channel": "youtube",
      "artist": "The Dead South",
      "tags": ["Music"],
      "url": "https://www.youtube.com/embed/zEf98SnGm-0?si=Yh0LTLTx_3WxyF9D"
    },
    {
      "id": 0,
      "name": "Wonderful New York in the early 1900s in color!",
      "description": "",
      "channel": "youtube",
      "artist": "",
      "tags": [],
      "url": "https://www.youtube.com/embed/85WMpJMv8aA?si=lCtSA1f3UB2Ircc-"
    },
    {
      "id": 0,
      "name": "Monty Python - French Taunting HD - The Full Version",
      "description": "French Taunting",
      "channel": "youtube",
      "artist": "Monty Python",
      "tags": ["Movies", "Monty Python"],
      "url": "https://www.youtube.com/embed/M9DCAFUerzs?si=fMOip6jxp5zHVLP0"
    },
    {
      "id": 0,
      "name": "Eric Idle - \"Always Look On The Bright Side Of Life\"",
      "description": "Always Look On The Bright Side Of Life",
      "channel": "youtube",
      "artist": "Eric Idle",
      "tags": ["Movies", "Monty Python"],
      "url": "https://www.youtube.com/embed/SJUhlRoBL8M?si=3jWebzG9xgbVs3pe"
    },
    {
      "id": 0,
      "name": "Fiddler on the roof - If I were a rich man",
      "description": "If I were a rich man",
      "channel": "youtube",
      "artist": "Topol",
      "tags": ["Movies"],
      "url": "https://www.youtube.com/embed/RBHZFYpQ6nc?si=GB0cdCGvn8T4I37R",
      "ranking": 0
    },
    {
      "id": 0,
      "name": "Les Misérables | Do You Hear the People Sing?",
      "description": "Do You Hear the People Sing",
      "channel": "youtube",
      "artist": "Ensemble",
      "tags": ["Les Misérables", "Musical"],
      "url": "https://www.youtube.com/embed/1q82twrdr0U?si=KbRX2skrOfCqa26p",
      "ranking": 1
    },
    {
      "id": 0,
      "name": "Colm Wilkinson - Bring Him Home (Les Misérables)",
      "description": "Bring Him Home",
      "channel": "youtube",
      "artist": "Colm Wilkinson",
      "tags": ["Les Misérables", "Musical"],
      "url": "https://www.youtube.com/embed/qsYnhVITf9E?si=Njoi_S6efJxvdy2c",
      "ranking": 1
    },
    {
      "id": 0,
      "name": "16 Tons - arranged by \"The Platters\"",
      "description": "16 Tons",
      "channel": "youtube",
      "artist": "The Platters",
      "tags": [""],
      "url": "https://www.youtube.com/embed/fjevsnCRQ_A?si=4ApUQc3TKuP7Zc4b"
    },
    {
      "id": 0,
      "name": "Come Out Ye Black And Tans (Cover) Colm R. McGuinness",
      "description": "Come Out Ye Black And Tans",
      "channel": "youtube",
      "artist": "Colm McGuinness",
      "section": "Irish Songs",
      "tags": ["Irish"],
      "url": "https://www.youtube.com/embed/PSxpL_UG8I4?si=5xmJ10nqnQMP1Zzt",
      "ranking": 1
    },
    {
      "id": 0,
      "name": "The Last Shanty",
      "description": "The Last Shanty",
      "channel": "youtube",
      "artist": "Colm McGuinness",
      "section": "Irish Songs",
      "tags": ["Irish"],
      "url": "https://www.youtube.com/embed/HFPStJrp9CI?si=FDgI_wki6e7pvoCW",
      "ranking": 1
    },
    {
      "id": 0,
      "name": "Amazing Grace (In Irish) - Colm R. McGuinness",
      "description": "Amazing Grace",
      "channel": "youtube",
      "artist": "Colm McGuinness",
      "section": "Irish Songs",
      "tags": ["Irish", "Favorites"],
      "url": "https://www.youtube.com/embed/PW0nMGCuwNQ?si=cCcLM2KN9I4NLPAN",
      "ranking": 0
    },
    {
      "id": 0,
      "name": "Auld Lang Syne (In Irish) - Colm R. McGuinness",
      "description": "Auld Lang Syne",
      "channel": "youtube",
      "artist": "Colm McGuinness",
      "section": "Irish Songs",
      "tags": ["Irish", "Favorites"],
      "url": "https://www.youtube.com/embed/1-9-o0rntTs?si=exK4-_BTPODUlwBs",
      "ranking": 0
    },
    {
      "id": 0,
      "name": "Auld Lang Syne",
      "description": "",
      "channel": "tiktok",
      "artist": "Sail North",
      "tags": [""],
      "url": "https://www.tiktok.com/@sailnorthmusic/video/7314686546685300011?is_from_webapp=1&sender_device=pc&web_id=7312218900903544351"
    }
  ],
  "channels": [
    {
      "id": 1,
      "channel": "youtube",
      "title": "Constantini Music",
      "url": "https://www.youtube.com/channel/UCfqS4jwdgdLf6oQZh7ipQlw",
      "tags": ["Claudio Constantini", "Constantini"]
    },
    {
      "id": 2,
      "channel": "youtube",
      "title": "Constantini Piano",
      "url": "https://www.youtube.com/@constantinipiano",
      "tags": ["Claudio Constantini", "Constantini", "piano"]
    },
    {
      "id": 3,
      "title": "Annie Lennox",
      "channel": "youtube",
      "url": "https://www.youtube.com/channel/UC1TecRIR-of2J6aBnEI_S_w",
      "tags": ["Annie Lennox"]
    },
    {
      "id": 4,
      "title": "Postmodern Jukebox",
      "channel": "youtube",
      "url": "https://www.youtube.com/@postmodernjukebox",
      "tags": ["Postmodern Jukebox"]
    },
    {
      "id": 5,
      "title": "Michael Bublé",
      "channel": "youtube",
      "url": "https://www.youtube.com/@michaelbuble",
      "tags": ["Michael Bublé"]
    },
    {
      "id": 6,
      "title": "",
      "channel": "youtube",
      "url": "",
      "tags": [""]
    },
    {
      "id": 3,
      "title": "",
      "channel": "youtube",
      "url": "",
      "tags": [""]
    },
    {
      "id": 7,
      "title": "",
      "channel": "youtube",
      "url": "",
      "tags": [""]
    }
  ]
}
